pyabst/__init__.py
pyabst-0.0.3.dist-info/LICENSE.txt
pyabst-0.0.3.dist-info/METADATA
pyabst-0.0.3.dist-info/WHEEL
pyabst-0.0.3.dist-info/top_level.txt
pyabst-0.0.3.dist-info/RECORD
