Metadata-Version: 2.1
Name: pyabst
Version: 0.0.3
Summary: A library which generates text summaries allowing users to weight significant or insignificant target words.
Home-page: https://github.com/joshuadavidwood
Author: Joshua David Wood
Author-email: pyaugment@gmail.com
License: UNKNOWN
Platform: UNKNOWN
Classifier: Programming Language :: Python :: 3
Classifier: License :: OSI Approved :: MIT License
Classifier: Operating System :: OS Independent
